miyadaiku/themes/jquery/__init__.py
miyadaiku/themes/jquery/config.yml
miyadaiku/themes/jquery/externals/jquery.js
miyadaiku/themes/jquery/externals/jquery.min.js
miyadaiku/themes/jquery/externals/jquery.slim.js
miyadaiku/themes/jquery/externals/jquery.slim.min.js
miyadaiku/themes/jquery/templates/macros.html
miyadaiku.themes.jquery-0.0.10.dist-info/DESCRIPTION.rst
miyadaiku.themes.jquery-0.0.10.dist-info/METADATA
miyadaiku.themes.jquery-0.0.10.dist-info/RECORD
miyadaiku.themes.jquery-0.0.10.dist-info/WHEEL
miyadaiku.themes.jquery-0.0.10.dist-info/metadata.json
miyadaiku.themes.jquery-0.0.10.dist-info/top_level.txt
