Metadata-Version: 2.0
Name: miyadaiku.themes.jquery
Version: 0.0.10
Summary: jQuery files for miyadaiku static site generator
Home-page: UNKNOWN
Author: Atsuo Ishimoto
Author-email: UNKNOWN
License: MIT
Platform: UNKNOWN
Classifier: Programming Language :: Python :: 3
Classifier: Programming Language :: Python :: 3.6
Requires-Dist: miyadaiku
